{
  "schemaVersion": "2.0",
  "glyph": {
    "char": "l",
    "case": "lower",
    "style": "cursive",
    "name": "traced lower l"
  },
  "guides": {
    "xHeight": 351.641149328859,
    "baseline": 924.3524538590602,
    "leftSidebearing": 524.3553048050047,
    "rightSidebearing": 744.7747845032231,
    "ascender": 45.734584731543464
  },
  "strokes": [
    {
      "kind": "stroke",
      "phase": "main",
      "segment": "lead-in",
      "curves": [
        {
          "p0": {
            "x": 105.9464928057554,
            "y": 922.7742805755395
          },
          "p1": {
            "x": 252.9196419209885,
            "y": 923.2662796228052
          },
          "p2": {
            "x": 529.0607234625508,
            "y": 716.9898033176394
          },
          "p3": {
            "x": 534.4811879619419,
            "y": 396.34266085504623
          },
          "segment": "lead-in"
        },
        {
          "p0": {
            "x": 534.4811879619419,
            "y": 396.34266085504623
          },
          "p1": {
            "x": 539.9016524613331,
            "y": 75.69551839245298
          },
          "p2": {
            "x": 549.1138458833447,
            "y": 124.46893061966946
          },
          "p3": {
            "x": 551.5974488549953,
            "y": 49.04332518749099
          },
          "segment": "entry"
        },
        {
          "p0": {
            "x": 551.5974488549953,
            "y": 49.04332518749099
          },
          "p1": {
            "x": 540.6203462888868,
            "y": 275.0649687549193
          },
          "p2": {
            "x": 523.7693199214312,
            "y": 571.5067536988296
          },
          "p3": {
            "x": 529.5072964500177,
            "y": 739.3352544926706
          },
          "segment": "body"
        },
        {
          "p0": {
            "x": 529.5072964500177,
            "y": 739.3352544926706
          },
          "p1": {
            "x": 535.2452729786042,
            "y": 907.1637552865117
          },
          "p2": {
            "x": 695.1254273490083,
            "y": 942.8776639279702
          },
          "p3": {
            "x": 801.1546539677133,
            "y": 902.0083968416393
          },
          "segment": "body"
        },
        {
          "p0": {
            "x": 801.1546539677133,
            "y": 902.0083968416393
          },
          "p1": {
            "x": 819.3655914677133,
            "y": 896.4385339819271
          },
          "p2": {
            "x": 848.1426260900155,
            "y": 886.9807439639414
          },
          "p3": {
            "x": 865.3054520792241,
            "y": 876.8855888380422
          },
          "segment": "lead-out"
        }
      ]
    }
  ]
}